HW4/verilog-BCD_counter/BCD.v
module BCD(clk, reset);
input clk , reset;
output [3:0] Q1; // O Result
reg [3:0] Q1;

always@ (posedge clk or posedge reset)
 begin
 if (reset)
    Q1 = 0;
 else if (Q1 == 9)
    Q1 = 0;
 else
    Q1 = Q1 + 1;
 end
endmodule

HW4/verilog-BCD_counter/BCD_tb.v
`timescale 1ns/1ps //設定時間參數

module BCD_tb();

reg clk, reset;
wire [3:0]Q1;
parameter PERIOD = 20;
parameter real DUTY_CYCLE = 0.5;
parameter OFFSET = 0; //呼叫 voter_if.v 的 module 

initial
    begin   
        #OFFSET;
        forever
            begin
                clk = 1'b0;
                #(PERIOD-(PERIOD*DUTY_CYCLE)) clk = 1'b1;
                #(PERIOD*DUTY_CYCLE);
            end
        end
initial begin
    reset = 1'b1;
    #5 reset = 1'b0;
    #150 reset = 1'b1;
    #5 reset = 1'b0;
    #300 $finish;
end
initial
    begin
        $dumpfile("BCD.vcd"); //指定vcd檔名為 voter_if.vcd
        $dumpvars(0,BCD_tb);  //紀錄voter_if_tb 模組及所有訊號
    end
BCD BCD_tb(
    .clk(clk),
    .reset(reset)
);
endmodule

HW4/verilog-BCD_counter/BCD.vcd
$date
	Fri Apr 22 16:28:30 2022
$end
$version
	Icarus Verilog
$end
$timescale
	1ps
$end
$scope module BCD_tb $end
$scope module BCD_tb $end
$var wire 1 ! clk $end
$var wire 1 " reset $end
$var reg 4 # Q1 [3:0] $end
$upscope $end
$upscope $end
$enddefinitions $end
#0
$dumpvars
b0 #
1"
0!
$end
#5000
0"
#10000
b1 #
1!
#20000
0!
#30000
b10 #
1!
#40000
0!
#50000
b11 #
1!
#60000
0!
#70000
b100 #
1!
#80000
0!
#90000
b101 #
1!
#100000
0!
#110000
b110 #
1!
#120000
0!
#130000
b111 #
1!
#140000
0!
#150000
b1000 #
1!
#155000
b0 #
1"
#160000
0"
0!
#170000
b1 #
1!
#180000
0!
#190000
b10 #
1!
#200000
0!
#210000
b11 #
1!
#220000
0!
#230000
b100 #
1!
#240000
0!
#250000
b101 #
1!
#260000
0!
#270000
b110 #
1!
#280000
0!
#290000
b111 #
1!
#300000
0!
#310000
b1000 #
1!
#320000
0!
#330000
b1001 #
1!
#340000
0!
#350000
b0 #
1!
#360000
0!
#370000
b1 #
1!
#380000
0!
#390000
b10 #
1!
#400000
0!
#410000
b11 #
1!
#420000
0!
#430000
b100 #
1!
#440000
0!
#450000
b101 #
1!
